{"title":"稍微知道了些要努力的方向","date":"2018-12-04T15:09:58.000Z","slug":"乾杯","updated":"2018-12-04T15:40:09.060Z","content":"<p>动画专业，可是并不是什么大学，而是技术学校，年龄不大，今年实际的年龄十五，如果按照身份证上的话十六（未来都会一直用身份证，所以就是十六啦）。<br>目前来说，根本看不出自己是动画专业的人，分镜，脚本，等一系列只听老师简单的讲过，以及自己网上搜了一些。<br>其实对现在的我来说，特别想做出一个好看的场景，<img src=\"imges-233.jpg\" width=\"500\" height=\"315\">应该是这样吧，3D方面我想做一个霓虹的建筑。<br>而至于MAD，我是想多了解一下分镜。至于我未来想干什么，我想从事动画后期或者脚本制作。（国漫脚本实在是有些无聊，因为并不太贴切，而突变英雄的对话我感到特别舒服…）<br>还是不太清楚自己要干什么，总之希望是动画方向的吧，至少要是动画方向的…（还有一年半就毕业了，其实是只有一年就毕业了，后半年就是实习了，我还未成年就要被打磨了233）<br>群里真的是很好玩啊，动画师加班回家，还经常下雨233（偶尔还经常忘记带外套（误））特喜欢雨天啊，但是同样也知道失落的时候雨天是什么滋味。</p>\n","next":{"title":"年轻的Mader","slug":"年轻的Mader"},"link":"http://github.com/Ransemo/ransemo.github.io/post/乾杯/"}